pyflipdot/__init__.py
pyflipdot/data.py
pyflipdot/pyflipdot.py
pyflipdot/sign.py
pyflipdot-0.2.2.dist-info/LICENSE
pyflipdot-0.2.2.dist-info/METADATA
pyflipdot-0.2.2.dist-info/WHEEL
pyflipdot-0.2.2.dist-info/top_level.txt
pyflipdot-0.2.2.dist-info/RECORD
