Metadata-Version: 2.1
Name: pyflipdot
Version: 0.2.2
Summary: Simple python driver for Hanover flipdot displays
Home-page: https://github.com/briggySmalls/pyflipdot
Author: Sam Briggs
Author-email: briggySmalls90@gmail.com
License: MIT license
Keywords: pyflipdot
Platform: UNKNOWN
Classifier: Development Status :: 2 - Pre-Alpha
Classifier: Intended Audience :: Developers
Classifier: License :: OSI Approved :: MIT License
Classifier: Natural Language :: English
Classifier: Programming Language :: Python :: 3
Classifier: Programming Language :: Python :: 3.5
Classifier: Programming Language :: Python :: 3.6
Classifier: Programming Language :: Python :: 3.7
Requires-Dist: numpy
Requires-Dist: pyserial
